larry/__init__.py
larry/twitter.py
larry_birdy-0.0.1.dist-info/LICENSE
larry_birdy-0.0.1.dist-info/METADATA
larry_birdy-0.0.1.dist-info/WHEEL
larry_birdy-0.0.1.dist-info/top_level.txt
larry_birdy-0.0.1.dist-info/RECORD
