Metadata-Version: 2.1
Name: larry-birdy
Version: 0.0.1
Summary: A proof-of-concept sentence-oriented Twitter API client for Python, based on 'birdy'.
Home-page: https://github.com/programmatizoumenos/larry-birdy
Author: programmatizoumenos
License: MIT
Keywords: twitter api tweet larry birdy search
Platform: UNKNOWN
Classifier: Programming Language :: Python :: 3
Classifier: License :: OSI Approved :: MIT License
Classifier: Operating System :: OS Independent
Requires-Dist: birdy
